crotal
tests
