Metadata-Version: 1.1
Name: crotal
Version: 0.9.8
Summary: A static site framework written in Python. Fast, powerful, and easy as 1, 2, 3.
Home-page: http://github.com/dinever/crotal
Author: Dinever
Author-email: dingpeixuan911@gmail.com
License: GNU GPLv3
Platform: UNKNOWN
Classifier: License :: OSI Approved :: GNU General Public License v3 (GPLv3)
Classifier: Operating System :: Microsoft :: Windows
Classifier: Operating System :: MacOS :: MacOS X
Classifier: Operating System :: POSIX
Classifier: Natural Language :: English
Classifier: Programming Language :: Python :: 2.5
Classifier: Programming Language :: Python :: 2.6
Classifier: Programming Language :: Python :: 2.7
Classifier: Programming Language :: Python :: 2 :: Only
